[
  {
    "id": 1,
    "songs": [
      {
        "album": "The Wind and The Star Traveler",
        "title": "Genshin Impact Main Theme",
        "youtubeId": "Mcz3yZSUVI8",
        "spotifyId": "6MZoXnbjDE2VgUWeMJgrrn",
        "fandomUrl": "/wiki/Genshin_Impact_Main_Theme"
      }
    ],
    "playedAt": {
      "main": "Login Menu (day)"
    },
    "type": "Special",
    "region": "Teyvat",
    "version": 1.0
  },
  {
    "id": 2,
    "songs": [
      {
        "album": "The Wind and The Star Traveler",
        "title": "Dawn Winery Theme",
        "youtubeId": "DVhcpUoku_U",
        "spotifyId": "3p19U1rci1sp5NfjReoN7W",
        "fandomUrl": "/wiki/Dawn_Winery_Theme_(The_Wind_and_The_Star_Traveler)"
      }
    ],
    "playedAt": {
      "main": "Dawn Winery (day)"
    },
    "type": "Special",
    "region": "Mondstadt",
    "version": 1.0
  },
  {
    "id": 3,
    "songs": [
      {
        "album": "The Wind and The Star Traveler",
        "title": "A Sweet Smile",
        "youtubeId": "TUqvYZn5nvc",
        "spotifyId": "7pI8KNXcE4jNeNjl0IJlfQ",
        "fandomUrl": "/wiki/A_Sweet_Smile"
      }
    ],
    "playedAt": {
      "main": "Prologue - Act I: The Outlander Who Caught the Wind",
      "sub": [
        "Leo Minor Chapter (Jean) - Act I: Master's Day Off",
        "Lepus Chapter (Amber) - Act I: Wind, Courage, and Wings"
      ]
    },
    "type": "Quest",
    "region": "Mondstadt",
    "version": 1.0
  },
  {
    "id": 4,
    "songs": [
      {
        "album": "The Wind and The Star Traveler",
        "title": "A Storm, A Spire, and a Sanctum (Dvalin's Nest)",
        "youtubeId": "NCv8RnC4v9g",
        "spotifyId": "1WMENm9ieRHQtStAsWlnTe",
        "fandomUrl": "/wiki/A_Storm,_A_Spire,_and_a_Sanctum_(Dvalin%27s_Nest)"
      }
    ],
    "playedAt": {
      "main": "Stormterror's Lair"
    },
    "type": "Ambient",
    "region": "Mondstadt",
    "version": 1.0
  },
  {
    "id": 5,
    "songs": [
      {
        "album": "The Wind and The Star Traveler",
        "title": "Caelestinum Finale Termini",
        "youtubeId": "ptrUUOxTF8c",
        "spotifyId": "4p5Zu3kpIELEebGeMNNiU3",
        "fandomUrl": "/wiki/Caelestinum_Finale_Termini"
      }
    ],
    "playedAt": {
      "main": "Stormterror Dvalin"
    },
    "type": "Boss",
    "region": "Mondstadt",
    "version": 1.0
  },
  {
    "id": 6,
    "songs": [
      {
        "album": "The Wind and The Star Traveler",
        "title": "Lone Sojourner",
        "youtubeId": "uZUdPd_PuJs",
        "spotifyId": "4UfRj8ikScFOs2WKzoR6En",
        "fandomUrl": "/wiki/Lone_Sojourner"
      }
    ],
    "playedAt": {
      "main": "Dawn Winery (night)"
    },
    "type": "Ambient",
    "region": "Mondstadt",
    "version": 1.0
  },
  {
    "id": 7,
    "songs": [
      {
        "album": "The Wind and The Star Traveler",
        "title": "A Day in Mondstadt",
        "youtubeId": "pWPpwQNxZTk",
        "spotifyId": "7KDvbvYwDksNnO5AI5xGHr",
        "fandomUrl": "/wiki/A_Day_in_Mondstadt"
      }
    ],
    "playedAt": {
      "main": "Mondstadt City (day)",
      "sub": ["Prologue - Act I: The Outlander Who Caught the Wind (cutscene)"]
    },
    "type": "Ambient",
    "region": "Mondstadt",
    "version": 1.0
  },
  {
    "id": 8,
    "songs": [
      {
        "album": "The Wind and The Star Traveler",
        "title": "Dream Aria",
        "youtubeId": "ghaz6x9Q-_4",
        "spotifyId": "602vSjoSXpRqpIFdaGEoW1",
        "fandomUrl": "/wiki/Dream_Aria_(Genshin_Impact_Main_Theme_Var.)"
      }
    ],
    "playedAt": {
      "main": "Login Menu (night)"
    },
    "type": "Special",
    "region": "Teyvat",
    "version": 1.0
  },
  {
    "id": 9,
    "songs": [
      {
        "album": "The Wind and The Star Traveler",
        "title": "Pure Sky",
        "youtubeId": "nIS-srtakdM",
        "spotifyId": "5pOJlpKwXNNKXp7lpFddy9",
        "fandomUrl": "/wiki/Pure_Sky"
      }
    ],
    "playedAt": {
      "main": "Mondstadt (day)"
    },
    "type": "Ambient",
    "region": "Mondstadt",
    "version": 1.0
  },
  {
    "id": 10,
    "songs": [
      {
        "album": "The Wind and The Star Traveler",
        "title": "The Edge of the Prairie",
        "youtubeId": "vsx15q1j3sc",
        "spotifyId": "1WlShbc4cKHDjjx5dpJbrg",
        "fandomUrl": "/wiki/The_Edge_of_the_Prairie"
      }
    ],
    "playedAt": {
      "main": "Mondstadt (rain)",
      "sub": ["Nameless Island"]
    },
    "type": "Ambient",
    "region": "Mondstadt",
    "version": 1.0
  },
  {
    "id": 11,
    "songs": [
      {
        "album": "The Wind and The Star Traveler",
        "title": "A Tale of Two Dragons",
        "youtubeId": "J4OWrg-joP4",
        "spotifyId": "0nN7UfpNf1qYkZdlAiSj6b",
        "fandomUrl": "/wiki/A_Tale_of_Two_Dragons"
      }
    ],
    "playedAt": {
      "main": "Prologue - Act II: For a Tomorrow Without Tears (cutscene)",
      "sub": [
        "Carmen Dei Chapter (Venti) - Act I: Should You Be Trapped in a Windless Land (cutscene)"
      ]
    },
    "type": "Quest",
    "region": "Mondstadt",
    "version": 1.0
  },
  {
    "id": 12,
    "songs": [
      {
        "album": "The Wind and The Star Traveler",
        "title": "Rite of Battle",
        "youtubeId": "mXH0qHk-fPQ",
        "spotifyId": "0a0aX3pR0WeW7ALwD9NHGX",
        "fandomUrl": "/wiki/Rite_of_Battle"
      }
    ],
    "playedAt": {
      "main": "Open-World Combat (Mondstadt & Golden Apple Archipelago)",
      "sub": ["Test Run - Character Trial"]
    },
    "type": "Combat",
    "region": "Mondstadt",
    "version": 1.0
  },
  {
    "id": 13,
    "songs": [
      {
        "album": "The Wind and The Star Traveler",
        "title": "Knighthood Excellence",
        "youtubeId": "SZBc_OTK16k",
        "spotifyId": "077mAoKu00E2c2JnhbUe7n",
        "fandomUrl": "/wiki/Knighthood_Excellence"
      }
    ],
    "playedAt": {
      "sub": [
        "Lepus Chapter (Amber) - Act I: Wind, Courage, and Wings",
        "Pavo Ocellus Chapter (Kaeya) - Act I: Secret Pirate Treasure"
      ]
    },
    "type": "Quest",
    "region": "Mondstadt",
    "version": 1.0
  },
  {
    "id": 14,
    "songs": [
      {
        "album": "The Wind and The Star Traveler",
        "title": "Happy Journey",
        "youtubeId": "b0A0d_Q8I40",
        "spotifyId": "6Ru3cXCSSxSHwPV7Gu6v39",
        "fandomUrl": "/wiki/Happy_Journey"
      }
    ],
    "playedAt": {
      "main": "Furball Fortress & Imaginarium Theater (lobby)",
      "sub": [
        "Leo Minor Chapter (Jean) - Act I: Master's Day Off",
        "Monoceros Caeli Chapter (Tartaglia) - Act I: Mighty Cyclops' Adventure! (cutscene)",
        "Trulla Chapter (Xiangling) - Act I: Mondstadt Gastronomy Trip"
      ]
    },
    "type": "Ambient",
    "region": "Mondstadt",
    "version": 1.0
  },
  {
    "id": 15,
    "songs": [
      {
        "album": "The Wind and The Star Traveler",
        "title": "The Outlander Who Caught the Wind",
        "youtubeId": "ROfl_4NUSZs",
        "spotifyId": "2otumcZdotztIUfRshnj0I",
        "fandomUrl": "/wiki/The_Outlander_Who_Caught_the_Wind_(Soundtrack)"
      }
    ],
    "playedAt": {
      "main": "Genshin Impact Trailer"
    },
    "type": "Special",
    "region": "Teyvat",
    "version": 1.0
  }
]
